libimgsmlr/Makefile
libimgsmlr/__init__.py
libimgsmlr/imgsmlr.c
libimgsmlr/imgsmlr.h
libimgsmlr/imgsmlr.py
libimgsmlr/libimgsmlr.so
libimgsmlr-0.1.6.dist-info/LICENSE
libimgsmlr-0.1.6.dist-info/METADATA
libimgsmlr-0.1.6.dist-info/WHEEL
libimgsmlr-0.1.6.dist-info/top_level.txt
libimgsmlr-0.1.6.dist-info/RECORD
