Metadata-Version: 2.1
Name: libimgsmlr
Version: 0.1.6
Summary: Implement the feature extraction function of the ``imgsmlr`` extension for ``PostgreSQL``.
Home-page: https://github.com/jie123108/libimgsmlr
Author: jie123108
Author-email: jie123108@163.com
Keywords: imgsmlr,postgres,image similarity search
License-File: LICENSE
Requires-Dist: filetype
